[
  {
    "id": "2025-26-G1-GEN-LEC",
    "matchday": 1,
    "date": "2025-08-23",
    "time": "18:30",
    "homeTeam": "Genoa",
    "awayTeam": "Lecce",
    "stadium": "Luigi Ferraris",
    "city": "Genova",
    "HomeGoals": 0,
    "AwayGoals": 0,
    "status": "FINISHED"
  },
  {
    "id": "2025-26-G1-SAS-NAP",
    "matchday": 1,
    "date": "2025-08-23",
    "time": "20:45",
    "homeTeam": "Sassuolo",
    "awayTeam": "Napoli",
    "stadium": "Mapei Stadium",
    "city": "Reggio Emilia",
    "HomeGoals": 0,
    "AwayGoals": 2,
    "status": "FINISHED"
  },
  {
    "id": "2025-26-G1-MIL-CRE",
    "matchday": 1,
    "date": "2025-08-24",
    "time": "12:30",
    "homeTeam": "AC Milan",
    "awayTeam": "Cremonese",
    "stadium": "San Siro",
    "city": "Milano",
    "HomeGoals": 1,
    "AwayGoals": 2,
    "status": "FINISHED"
  },
  {
    "id": "2025-26-G1-CAG-FIO",
    "matchday": 1,
    "date": "2025-08-24",
    "time": "15:00",
    "homeTeam": "Cagliari",
    "awayTeam": "Fiorentina",
    "stadium": "Unipol Domus",
    "city": "Cagliari",
    "HomeGoals": 1,
    "AwayGoals": 1,
    "status": "FINISHED"
  },
  {
    "id": "2025-26-G1-COM-LAZ",
    "matchday": 1,
    "date": "2025-08-24",
    "time": "15:00",
    "homeTeam": "Como",
    "awayTeam": "Lazio",
    "stadium": "Giuseppe Sinigaglia",
    "city": "Como",
    "HomeGoals": 2,
    "AwayGoals": 0,
    "status": "FINISHED"
  },
  {
    "id": "2025-26-G1-ATA-PIS",
    "matchday": 1,
    "date": "2025-08-24",
    "time": "15:00",
    "homeTeam": "Atalanta",
    "awayTeam": "Pisa",
    "stadium": "Gewiss Stadium",
    "city": "Bergamo",
    "HomeGoals": 1,
    "AwayGoals": 1,
    "status": "FINISHED"
  },
  {
    "id": "2025-26-G1-JUV-PAR",
    "matchday": 1,
    "date": "2025-08-24",
    "time": "18:30",
    "homeTeam": "Juventus",
    "awayTeam": "Parma",
    "stadium": "Allianz Stadium",
    "city": "Torino",
    "HomeGoals": 2,
    "AwayGoals": 0,
    "status": "FINISHED"
  },
  {
    "id": "2025-26-G1-ROM-BOL",
    "matchday": 1,
    "date": "2025-08-24",
    "time": "20:45",
    "homeTeam": "Roma",
    "awayTeam": "Bologna",
    "stadium": "Olimpico",
    "city": "Roma",
    "HomeGoals": 1,
    "AwayGoals": 0,
    "status": "FINISHED"
  },
  {
    "id": "2025-26-G1-UDI-VER",
    "matchday": 1,
    "date": "2025-08-25",
    "time": "18:30",
    "homeTeam": "Udinese",
    "awayTeam": "Hellas Verona",
    "stadium": "Bluenergy Stadium",
    "city": "Udine",
    "HomeGoals": 1,
    "AwayGoals": 1,
    "status": "FINISHED"
  },
  {
    "id": "2025-26-G1-INT-TOR",
    "matchday": 1,
    "date": "2025-08-25",
    "time": "20:45",
    "homeTeam": "Inter",
    "awayTeam": "Torino",
    "stadium": "San Siro",
    "city": "Milano",
    "HomeGoals": 5,
    "AwayGoals": 0,
    "status": "FINISHED"
  },
  {
    "id": "2025-26-G2-NAP-CRE",
    "matchday": 2,
    "date": "2025-08-30",
    "time": "18:30",
    "homeTeam": "Napoli",
    "awayTeam": "Cremonese",
    "stadium": "Diego Armando Maradona",
    "city": "Napoli",
    "HomeGoals": 2,
    "AwayGoals": 0,
    "status": "FINISHED"
  }
]